{
  "kind": "collectionType",
  "collectionName": "contacts",
  "info": {
    "singularName": "contact",
    "pluralName": "contacts",
    "displayName": "Contact",
    "description": ""
  },
  "options": {
    "draftAndPublish": true
  },
  "pluginOptions": {},
  "attributes": {
    "name": {
      "type": "string",
      "required": true
    },
    "email": {
      "type": "email",
      "required": true
    },
    "number": {
      "type": "string",
      "regex": "^(\\+92|0092|92|0)?3\\d{9}$",
      "required": true
    },
    "message": {
      "type": "text",
      "required": true
    }
  }
}
